caseSelector2/__init__.py
caseSelector2/__main__.py
helloCaseHW-1.0.1.dist-info/METADATA
helloCaseHW-1.0.1.dist-info/WHEEL
helloCaseHW-1.0.1.dist-info/top_level.txt
helloCaseHW-1.0.1.dist-info/RECORD
