Metadata-Version: 2.1
Name: helloCaseHW
Version: 1.0.1
Summary: UNKNOWN
Home-page: UNKNOWN
Author: Chhavi Trivedi
Author-email: UNKNOWN
License: MIT
Platform: UNKNOWN
Classifier: License :: OSI Approved :: MIT License
Classifier: Programming Language :: Python :: 3
Classifier: Programming Language :: Python :: 3.7
Requires-Dist: pathlib
